{
  "MAD": "Madrid",
  "BCN": "Barcelona",
  "AGP": "Málaga",
  "SVQ": "Sevilla",
  "VLC": "Valencia",
  "PMI": "Palma de Mallorca",
  "IBZ": "Ibiza",
  "ALC": "Alicante",
  "LPA": "Las Palmas (Gran Canaria)",
  "TFN": "Tenerife Norte",
  "TFS": "Tenerife Sur",
  "SPC": "La Palma",
  "BIO": "Bilbao",
  "SCQ": "Santiago de Compostela",
  "LCG": "A Coruña",
  "VGO": "Vigo",
  "OVD": "Asturias (Oviedo)",
  "SDR": "Santander",
  "GRX": "Granada",
  "XRY": "Jerez de la Frontera",
  "FUE": "Fuerteventura",
  "ACE": "Lanzarote",
  "MAH": "Menorca",
  "REU": "Reus",
  "GRO": "Girona",
  "ZAZ": "Zaragoza",
  "EAS": "San Sebastián",
  "PNA": "Pamplona",
  "VLL": "Valladolid",
  "RJL": "Logroño",
  "LEN": "León",

  "LIS": "Lisboa",
  "OPO": "Oporto",
  "FAO": "Faro",
  "FNC": "Funchal (Madeira)",
  "PDL": "Ponta Delgada (Azores)",
  "TER": "Terceira (Azores)",
  "HOR": "Horta (Azores)",
  "PIX": "Pico (Azores)",

  "CDG": "París (Charles de Gaulle)",
  "ORY": "París (Orly)",
  "BVA": "París (Beauvais)",
  "NCE": "Niza",
  "MRS": "Marsella",
  "LYS": "Lyon",
  "TLS": "Toulouse",
  "BOD": "Burdeos",
  "NTE": "Nantes",
  "LIL": "Lille",
  "AJA": "Ajaccio",
  "BIA": "Bastia",

  "AMS": "Ámsterdam",
  "EIN": "Eindhoven",
  "RTM": "Róterdam/La Haya",

  "BRU": "Bruselas",
  "CRL": "Bruselas (Charleroi)",

  "FRA": "Fráncfort",
  "MUC": "Múnich",
  "BER": "Berlín",
  "DUS": "Düsseldorf",
  "CGN": "Colonia/Bonn",
  "HAM": "Hamburgo",
  "STR": "Stuttgart",
  "HAJ": "Hanóver",
  "NUE": "Núremberg",
  "LEJ": "Leipzig/Halle",
  "FMM": "Memmingen",
  "FKB": "Karlsruhe/Baden-Baden",

  "ZRH": "Zúrich",
  "GVA": "Ginebra",
  "BSL": "Basilea/Mulhouse",

  "VIE": "Viena",
  "SZG": "Salzburgo",
  "INN": "Innsbruck",
  "GRZ": "Graz",
  "LNZ": "Linz",
  "KLU": "Klagenfurt",

  "PRG": "Praga",
  "BUD": "Budapest",

  "WAW": "Varsovia (Chopin)",
  "WMI": "Varsovia (Modlin)",
  "KRK": "Cracovia",
  "GDN": "Gdansk",
  "WRO": "Breslavia",
  "POZ": "Poznan",
  "KTW": "Katowice",
  "RZE": "Rzeszów",

  "ATH": "Atenas",
  "SKG": "Salónica",
  "HER": "Heraclión (Creta)",
  "RHO": "Rodas",
  "CFU": "Corfú",
  "CHQ": "Chania (Creta)",
  "JTR": "Santorini",
  "JMK": "Mikonos",
  "KGS": "Kos",
  "ZTH": "Zante (Zakynthos)",

  "IST": "Estambul (IST)",
  "SAW": "Estambul (Sabiha Gökçen)",
  "AYT": "Antalya",
  "ESB": "Ankara",
  "ADB": "Esmirna (İzmir)",

  "RAK": "Marrakech",
  "CMN": "Casablanca",
  "TNG": "Tánger",
  "FEZ": "Fez",
  "AGA": "Agadir",
  "RBA": "Rabat",
  "OUD": "Oujda",
  "OZZ": "Uarzazat",

  "LHR": "Londres (Heathrow)",
  "LGW": "Londres (Gatwick)",
  "LTN": "Londres (Luton)",
  "STN": "Londres (Stansted)",
  "LCY": "Londres (City)",
  "MAN": "Mánchester",
  "LPL": "Liverpool",
  "BHX": "Birmingham",
  "EMA": "East Midlands",
  "EDI": "Edimburgo",
  "GLA": "Glasgow",
  "ABZ": "Aberdeen",
  "NCL": "Newcastle",
  "BRS": "Bristol",
  "CWL": "Cardiff",
  "LBA": "Leeds/Bradford",
  "BFS": "Belfast (International)",
  "BHD": "Belfast City",

  "DUB": "Dublín",
  "SNN": "Shannon",
  "ORK": "Cork",

  "CPH": "Copenhague",
  "BLL": "Billund",
  "AAL": "Aalborg",

  "ARN": "Estocolmo (Arlanda)",
  "BMA": "Estocolmo (Bromma)",
  "GOT": "Gotemburgo (Landvetter)",
  "MMX": "Malmö",

  "OSL": "Oslo (Gardermoen)",
  "BGO": "Bergen",
  "SVG": "Stavanger",
  "TRD": "Trondheim",

  "HEL": "Helsinki",
  "RVN": "Rovaniemi",
  "OUL": "Oulu",

  "MEX": "Ciudad de México (AICM)",
  "NLU": "Felipe Ángeles (CDMX)",
  "TLC": "Toluca",
  "GDL": "Guadalajara",
  "MTY": "Monterrey",
  "CUN": "Cancún",
  "CZM": "Cozumel",
  "TQO": "Tulum (Felipe Carrillo Puerto)",
  "HUX": "Huatulco",
  "PVR": "Puerto Vallarta",
  "ACA": "Acapulco",
  "SJD": "San José del Cabo (Los Cabos)",
  "TIJ": "Tijuana",
  "MXL": "Mexicali",
  "MID": "Mérida",
  "VER": "Veracruz",
  "TAM": "Tampico",
  "VSA": "Villahermosa",
  "TGZ": "Tuxtla Gutiérrez",
  "CPE": "Campeche",
  "CJS": "Ciudad Juárez",
  "CUU": "Chihuahua",
  "DGO": "Durango",
  "ZLO": "Manzanillo",
  "LAP": "La Paz",
  "LMM": "Los Mochis",
  "PBC": "Puebla",
  "PXM": "Puerto Escondido",
  "TRC": "Torreón",
  "UPN": "Uruapan",
  "ZCL": "Zacatecas",
  "SLW": "Saltillo",
  "MZT": "Mazatlán",
  "BJX": "León/Guanajuato",
  "QRO": "Querétaro",
  "HMO": "Hermosillo",
  "OAX": "Oaxaca",
  "ZIH": "Ixtapa-Zihuatanejo",

  "JFK": "Nueva York (JFK)",
  "LGA": "Nueva York (LaGuardia)",
  "EWR": "Newark",
  "BOS": "Boston",
  "IAD": "Washington Dulles",
  "DCA": "Washington National (Reagan)",
  "PHL": "Filadelfia",
  "PIT": "Pittsburgh",
  "CLE": "Cleveland",
  "DTW": "Detroit",
  "ORD": "Chicago O’Hare",
  "MDW": "Chicago Midway",
  "MSP": "Minneapolis–St. Paul",
  "MKE": "Milwaukee",
  "STL": "San Luis",
  "BNA": "Nashville",
  "ATL": "Atlanta",
  "CLT": "Charlotte",
  "RDU": "Raleigh–Durham",
  "MCO": "Orlando",
  "TPA": "Tampa",
  "MIA": "Miami",
  "FLL": "Fort Lauderdale",
  "PBI": "West Palm Beach",
  "RSW": "Fort Myers",
  "JAX": "Jacksonville",
  "MSY": "Nueva Orleans",
  "IAH": "Houston (Intercontinental)",
  "HOU": "Houston (Hobby)",
  "DFW": "Dallas/Fort Worth",
  "DAL": "Dallas (Love Field)",
  "AUS": "Austin",
  "SAT": "San Antonio",
  "DEN": "Denver",
  "PHX": "Phoenix",
  "LAS": "Las Vegas",
  "SLC": "Salt Lake City",
  "SEA": "Seattle/Tacoma",
  "PDX": "Portland",
  "LAX": "Los Ángeles",
  "BUR": "Burbank",
  "LGB": "Long Beach",
  "SNA": "Santa Ana (Orange County)",
  "ONT": "Ontario (California)",
  "SAN": "San Diego",
  "SFO": "San Francisco",
  "OAK": "Oakland",
  "SJC": "San José (California)",
  "SMF": "Sacramento",
  "RNO": "Reno",
  "BOI": "Boise",

  "YYZ": "Toronto (Pearson)",
  "YTZ": "Toronto (Billy Bishop)",
  "YUL": "Montreal (Trudeau)",
  "YVR": "Vancouver",
  "YYC": "Calgary",
  "YEG": "Edmonton",
  "YOW": "Ottawa",
  "YQB": "Quebec",
  "YHZ": "Halifax",
  "YWG": "Winnipeg",
  "YXE": "Saskatoon"
}
